libpass/__init__.py
libpass/_salt.py
libpass/context.py
libpass/errors.py
libpass/py.typed
libpass/_utils/__init__.py
libpass/_utils/b64.py
libpass/_utils/binary.py
libpass/_utils/bytes.py
libpass/_utils/const.py
libpass/_utils/deprecated.py
libpass/_utils/protocols.py
libpass/_utils/str.py
libpass/_utils/validation.py
libpass/hashers/__init__.py
libpass/hashers/abc.py
libpass/hashers/argon2.py
libpass/hashers/bcrypt.py
libpass/hashers/django.py
libpass/hashers/pbkdf2.py
libpass/hashers/sha_crypt.py
libpass/hashers/unix_disabled.py
libpass/inspect/__init__.py
libpass/inspect/bcrypt.py
libpass/inspect/django.py
libpass/inspect/pbkdf2.py
libpass/inspect/sha_crypt.py
libpass/inspect/phc/__init__.py
libpass/inspect/phc/_phc.py
libpass/inspect/phc/defs.py
libpass_next-0.3.0.dist-info/METADATA
libpass_next-0.3.0.dist-info/WHEEL
libpass_next-0.3.0.dist-info/top_level.txt
libpass_next-0.3.0.dist-info/RECORD
