Metadata-Version: 2.4
Name: libpass-next
Version: 0.3.0
Summary: Password hashing library, rewrite of passlib.
Author-email: Doctor <notypecheck@gmail.com>
Classifier: Intended Audience :: Developers
Classifier: Operating System :: OS Independent
Classifier: Programming Language :: Python :: 3
Classifier: Programming Language :: Python :: 3.9
Classifier: Programming Language :: Python :: 3.10
Classifier: Programming Language :: Python :: 3.11
Classifier: Programming Language :: Python :: 3.12
Classifier: Programming Language :: Python :: 3.13
Classifier: Programming Language :: Python :: Implementation :: CPython
Classifier: Topic :: Security :: Cryptography
Classifier: Topic :: Software Development :: Libraries
Requires-Python: >=3.9
Requires-Dist: typing-extensions>=4.6.0
Provides-Extra: bcrypt
Requires-Dist: bcrypt>=4.3.0; extra == "bcrypt"
Provides-Extra: argon
Requires-Dist: argon2-cffi>=25.1.0; extra == "argon"
